resworb/__init__.py
resworb/base.py
resworb/browsers/__init__.py
resworb/browsers/chrome.py
resworb/browsers/firefox.py
resworb/browsers/safari.py
resworb/commands/safari_export.py
resworb/commands/safari_main.py
resworb/exporter.py
resworb-0.2.1.dist-info/WHEEL
resworb-0.2.1.dist-info/METADATA
resworb-0.2.1.dist-info/RECORD
