Metadata-Version: 2.1
Name: resworb
Version: 0.2.1
Summary: Manage browser data in Python.
Author: Yevgnen Koh
Author-email: wherejoystarts@gmail.com
Requires-Python: >=3.8,<4.0
Classifier: Programming Language :: Python :: 3
Classifier: Programming Language :: Python :: 3.10
Classifier: Programming Language :: Python :: 3.8
Classifier: Programming Language :: Python :: 3.9
Requires-Dist: PyYAML (>=5.4.1,<6.0.0)
Requires-Dist: lz4 (>=3.1.3,<4.0.0)
Requires-Dist: pytoml (>=0.1.21,<0.2.0)
